rembg/__init__.py
rembg/basic_greenscreen.py
rembg/bg.py
rembg/multiprocessing.py
rembg/test.py
rembg/cmd/__init__.py
rembg/cmd/cli.py
rembg/u2net/__init__.py
rembg/u2net/detect.py
rembg/u2net/u2net.py
rembg_greenscreen-2.1.10.dist-info/LICENSE.txt
rembg_greenscreen-2.1.10.dist-info/METADATA
rembg_greenscreen-2.1.10.dist-info/WHEEL
rembg_greenscreen-2.1.10.dist-info/entry_points.txt
rembg_greenscreen-2.1.10.dist-info/top_level.txt
rembg_greenscreen-2.1.10.dist-info/RECORD
