Metadata-Version: 2.1
Name: rembg-greenscreen
Version: 2.1.10
Summary: Rembg Virtual Green Screen
Home-page: https://github.com/ecsplendid/rembg-greenscreen
Author: Tim Scarfe
Author-email: tim@developer-x.com
License: UNKNOWN
Keywords: remove,background,u2net,greenscreen,green screen,matte
Platform: UNKNOWN
Classifier: License :: OSI Approved :: MIT License
Classifier: Programming Language :: Python :: 3 :: Only
Requires-Python: >=3.8, <4
Requires-Dist: numpy (==1.19.4)
Requires-Dist: torchvision
Requires-Dist: tqdm (==4.56.0)
Requires-Dist: more-itertools (==8.7.0)
Requires-Dist: moviepy (==1.0.3)
Requires-Dist: ffmpeg-python (==0.2.0)
Requires-Dist: torch
Requires-Dist: scikit-image (==0.17.2)
Requires-Dist: requests (==2.25.1)
Requires-Dist: hsh (==1.1.0)
Requires-Dist: Pillow (==8.1.0)
Requires-Dist: ffmpeg-python
